[{"year":1950,"catch":37},{"year":1951,"catch":80},{"year":1952,"catch":38},{"year":1953,"catch":129},{"year":1954,"catch":24},{"year":1955,"catch":24},{"year":1956,"catch":23},{"year":1957,"catch":15},{"year":1958,"catch":19},{"year":1959,"catch":20},{"year":1960,"catch":19},{"year":1961,"catch":15},{"year":1962,"catch":21},{"year":1963,"catch":33},{"year":1964,"catch":32},{"year":1965,"catch":39},{"year":1966,"catch":3132},{"year":1967,"catch":183},{"year":1968,"catch":4801},{"year":1969,"catch":7378},{"year":1970,"catch":3558},{"year":1971,"catch":17302},{"year":1972,"catch":7179},{"year":1973,"catch":17460},{"year":1974,"catch":12917},{"year":1975,"catch":21517},{"year":1976,"catch":4633},{"year":1977,"catch":7233},{"year":1978,"catch":2493},{"year":1979,"catch":2919},{"year":1980,"catch":3567},{"year":1981,"catch":2457},{"year":1982,"catch":1307},{"year":1983,"catch":3001},{"year":1984,"catch":3528},{"year":1985,"catch":4859},{"year":1986,"catch":4621},{"year":1987,"catch":11739},{"year":1988,"catch":9583},{"year":1989,"catch":13438},{"year":1990,"catch":13009},{"year":1991,"catch":14623},{"year":1992,"catch":18066},{"year":1993,"catch":20368},{"year":1994,"catch":21480},{"year":1995,"catch":26871},{"year":1996,"catch":25826},{"year":1997,"catch":29580},{"year":1998,"catch":27844},{"year":1999,"catch":26320},{"year":2000,"catch":22075},{"year":2001,"catch":25178},{"year":2002,"catch":26756},{"year":2003,"catch":30721},{"year":2004,"catch":23554},{"year":2005,"catch":21501},{"year":2006,"catch":16512},{"year":2007,"catch":12692},{"year":2008,"catch":11480},{"year":2009,"catch":9130},{"year":2010,"catch":7686},{"year":2011,"catch":9122}]
