[{"year":1950,"catch":43120},{"year":1951,"catch":38022},{"year":1952,"catch":48339},{"year":1953,"catch":39931},{"year":1954,"catch":27806},{"year":1955,"catch":21765},{"year":1956,"catch":26322},{"year":1957,"catch":27234},{"year":1958,"catch":13045},{"year":1959,"catch":21636},{"year":1960,"catch":29876},{"year":1961,"catch":38784},{"year":1962,"catch":36352},{"year":1963,"catch":49301},{"year":1964,"catch":40429},{"year":1965,"catch":28992},{"year":1966,"catch":23639},{"year":1967,"catch":31720},{"year":1968,"catch":53135},{"year":1969,"catch":27401},{"year":1970,"catch":34900},{"year":1971,"catch":43300},{"year":1972,"catch":24400},{"year":1973,"catch":17100},{"year":1974,"catch":20624},{"year":1975,"catch":10421},{"year":1976,"catch":66846},{"year":1977,"catch":54992},{"year":1978,"catch":69869},{"year":1979,"catch":60728},{"year":1980,"catch":78966},{"year":1981,"catch":72500},{"year":1982,"catch":125059},{"year":1983,"catch":134022},{"year":1984,"catch":83377},{"year":1985,"catch":92765},{"year":1986,"catch":60634},{"year":1987,"catch":50589},{"year":1988,"catch":33012},{"year":1989,"catch":28385},{"year":1990,"catch":48341},{"year":1991,"catch":31331},{"year":1992,"catch":47598},{"year":1993,"catch":70048},{"year":1994,"catch":59296},{"year":1995,"catch":105428},{"year":1996,"catch":82119},{"year":1997,"catch":61640},{"year":1998,"catch":75490},{"year":1999,"catch":49111},{"year":2000,"catch":153291},{"year":2001,"catch":113290},{"year":2002,"catch":103657},{"year":2003,"catch":114723},{"year":2004,"catch":61396},{"year":2005,"catch":72807},{"year":2006,"catch":37733},{"year":2007,"catch":50918},{"year":2008,"catch":39196},{"year":2009,"catch":48316},{"year":2010,"catch":17363},{"year":2011,"catch":27480},{"year":2012,"catch":42899},{"year":2013,"catch":31849},{"year":2014,"catch":11743}]
