[{"year":1950,"catch":42900},{"year":1951,"catch":42600},{"year":1952,"catch":55500},{"year":1953,"catch":47800},{"year":1954,"catch":44600},{"year":1955,"catch":51000},{"year":1956,"catch":55000},{"year":1957,"catch":54100},{"year":1958,"catch":47200},{"year":1959,"catch":62300},{"year":1960,"catch":62700},{"year":1961,"catch":52500},{"year":1962,"catch":70700},{"year":1963,"catch":78300},{"year":1964,"catch":47700},{"year":1965,"catch":43500},{"year":1966,"catch":53700},{"year":1967,"catch":60000},{"year":1968,"catch":52600},{"year":1969,"catch":54500},{"year":1970,"catch":57300},{"year":1971,"catch":65700},{"year":1972,"catch":75300},{"year":1973,"catch":82100},{"year":1974,"catch":78853},{"year":1975,"catch":110285},{"year":1976,"catch":152523},{"year":1977,"catch":203450},{"year":1978,"catch":224412},{"year":1979,"catch":204400},{"year":1980,"catch":236607},{"year":1981,"catch":217870},{"year":1982,"catch":242391},{"year":1983,"catch":218286},{"year":1984,"catch":149038},{"year":1985,"catch":181241},{"year":1986,"catch":155815},{"year":1987,"catch":160891},{"year":1988,"catch":147415},{"year":1989,"catch":192748},{"year":1990,"catch":162541},{"year":1991,"catch":113536},{"year":1992,"catch":111198},{"year":1993,"catch":61767},{"year":1994,"catch":91145},{"year":1995,"catch":110441},{"year":1996,"catch":121758},{"year":1997,"catch":63116},{"year":1998,"catch":56854},{"year":1999,"catch":56575},{"year":2000,"catch":49607},{"year":2001,"catch":46519},{"year":2002,"catch":49694},{"year":2003,"catch":53399},{"year":2004,"catch":41835},{"year":2005,"catch":52830},{"year":2006,"catch":38713},{"year":2007,"catch":47744},{"year":2008,"catch":46166},{"year":2009,"catch":40932},{"year":2010,"catch":44612},{"year":2011,"catch":41928},{"year":2012,"catch":42417},{"year":2013,"catch":44499},{"year":2014,"catch":34292}]
