[{"year":1950,"catch":18495},{"year":1951,"catch":17874},{"year":1952,"catch":17790},{"year":1953,"catch":23886},{"year":1954,"catch":23073},{"year":1955,"catch":27488},{"year":1956,"catch":21508},{"year":1957,"catch":23927},{"year":1958,"catch":27664},{"year":1959,"catch":32483},{"year":1960,"catch":39413},{"year":1961,"catch":36529},{"year":1962,"catch":31817},{"year":1963,"catch":35849},{"year":1964,"catch":36094},{"year":1965,"catch":39648},{"year":1966,"catch":34333},{"year":1967,"catch":31731},{"year":1968,"catch":29764},{"year":1969,"catch":35709},{"year":1970,"catch":30000},{"year":1971,"catch":30266},{"year":1972,"catch":32715},{"year":1973,"catch":37236},{"year":1974,"catch":37195},{"year":1975,"catch":31006},{"year":1976,"catch":28933},{"year":1977,"catch":31669},{"year":1978,"catch":36997},{"year":1979,"catch":38228},{"year":1980,"catch":37824},{"year":1981,"catch":37255},{"year":1982,"catch":35640},{"year":1983,"catch":34530},{"year":1984,"catch":42362},{"year":1985,"catch":38312},{"year":1986,"catch":38289},{"year":1987,"catch":44010},{"year":1988,"catch":51187},{"year":1989,"catch":39392},{"year":1990,"catch":34167},{"year":1991,"catch":42455},{"year":1992,"catch":51959},{"year":1993,"catch":47564},{"year":1994,"catch":63399},{"year":1995,"catch":44564},{"year":1996,"catch":43819},{"year":1997,"catch":53591},{"year":1998,"catch":56612},{"year":1999,"catch":43391},{"year":2000,"catch":51160},{"year":2001,"catch":44486},{"year":2002,"catch":51844},{"year":2003,"catch":56141},{"year":2004,"catch":52631},{"year":2005,"catch":49836},{"year":2006,"catch":55657},{"year":2007,"catch":48904},{"year":2008,"catch":38622},{"year":2009,"catch":46899},{"year":2010,"catch":36855},{"year":2011,"catch":46306},{"year":2012,"catch":49220},{"year":2013,"catch":43499},{"year":2014,"catch":40348}]
